mindforge/__init__.py
mindforge/browser_client.py
mindforge/messages.py
mindforge/server_client.py
mindforge/token.py
mindforge-1.0.4.dist-info/METADATA
mindforge-1.0.4.dist-info/WHEEL
mindforge-1.0.4.dist-info/licenses/LICENSE
mindforge-1.0.4.dist-info/RECORD
