Metadata-Version: 2.3
Name: mindforge
Version: 1.0.4
Summary: Python client for mindforge.ai
Project-URL: Homepage, https://mindforge.ai
Project-URL: Repository, https://github.com/mindforge-ai/mindforge-py
Author-email: William Eliot <william@mindforge.ai>
License-File: LICENSE
Classifier: License :: OSI Approved :: MIT License
Classifier: Operating System :: OS Independent
Classifier: Programming Language :: Python :: 3
Requires-Python: >=3.8
Requires-Dist: events>=0.5
Requires-Dist: livekit>=0.17.5
Requires-Dist: weboscket-client>=1.8.0
